distributions/Binomialdistribution.py
distributions/Gaussiandistribution.py
distributions/Generaldistribution.py
distributions/__init__.py
distributions_abel_keya-0.1.dist-info/METADATA
distributions_abel_keya-0.1.dist-info/WHEEL
distributions_abel_keya-0.1.dist-info/top_level.txt
distributions_abel_keya-0.1.dist-info/RECORD
